lslgwclient/__init__.py
lslgwclient/client/api.py
lslgwclient/client/basehttp.py
lslgwclient/client/container.py
lslgwclient/client/http.py
lslgwclient/client/linkset.py
lslgwclient/exceptions/__init__.py
lslgwclient/exceptions/linksetdata.py
lslgwclient/models/__init__.py
lslgwclient/models/lslresponse.py
lslgwclient/py.typed
lsl_gateway_client-24.8.0.dist-info/LICENSE-lgpl-3.0.md
lsl_gateway_client-24.8.0.dist-info/METADATA
lsl_gateway_client-24.8.0.dist-info/WHEEL
lsl_gateway_client-24.8.0.dist-info/RECORD
